game_files/__init__.py
game_files/main.py
terminal_cricket-1.1.0.dist-info/METADATA
terminal_cricket-1.1.0.dist-info/WHEEL
terminal_cricket-1.1.0.dist-info/entry_points.txt
terminal_cricket-1.1.0.dist-info/top_level.txt
terminal_cricket-1.1.0.dist-info/RECORD
