Metadata-Version: 2.1
Name: terminal-cricket
Version: 1.1.0
Summary: A simple terminal game depicting cricket
Home-page: https://github.com/ezazaa/terminal-cricket
Author: Ezaz Alam Ahmed 
Author-email: ezazalamahmed@gmail.com
Classifier: Programming Language :: Python :: 3
Classifier: License :: OSI Approved :: MIT License
Classifier: Operating System :: OS Independent
Requires-Dist: colorama
